setup.py
djangox/__init__.py
djangox/mako/__init__.py
djangox/mako/shortcuts.py
djangox_mako.egg-info/PKG-INFO
djangox_mako.egg-info/SOURCES.txt
djangox_mako.egg-info/dependency_links.txt
djangox_mako.egg-info/namespace_packages.txt
djangox_mako.egg-info/requires.txt
djangox_mako.egg-info/top_level.txt