Metadata-Version: 1.1
Name: djangox-mako
Version: 1.0.7
Summary: Mako template adapter for django.
Home-page: https://github.com/youngrok/djangox-mako
Author: Youngrok Pak
Author-email: pak.youngrok@gmail.com
License: UNKNOWN
Keywords: mako django djangox
Platform: UNKNOWN
Classifier: Development Status :: 3 - Alpha
Classifier: Topic :: Software Development :: Libraries
Classifier: License :: OSI Approved :: BSD License
